odoo10_addon_sale_order_action_invoice_create_hook-10.0.1.0.0-py2.7-nspkg.pth
odoo/addons/sale_order_action_invoice_create_hook/README.rst
odoo/addons/sale_order_action_invoice_create_hook/__init__.py
odoo/addons/sale_order_action_invoice_create_hook/__manifest__.py
odoo/addons/sale_order_action_invoice_create_hook/model/__init__.py
odoo/addons/sale_order_action_invoice_create_hook/model/sale_order.py
odoo/addons/sale_order_action_invoice_create_hook/static/description/icon.png
odoo10_addon_sale_order_action_invoice_create_hook-10.0.1.0.0.dist-info/DESCRIPTION.rst
odoo10_addon_sale_order_action_invoice_create_hook-10.0.1.0.0.dist-info/METADATA
odoo10_addon_sale_order_action_invoice_create_hook-10.0.1.0.0.dist-info/RECORD
odoo10_addon_sale_order_action_invoice_create_hook-10.0.1.0.0.dist-info/WHEEL
odoo10_addon_sale_order_action_invoice_create_hook-10.0.1.0.0.dist-info/metadata.json
odoo10_addon_sale_order_action_invoice_create_hook-10.0.1.0.0.dist-info/namespace_packages.txt
odoo10_addon_sale_order_action_invoice_create_hook-10.0.1.0.0.dist-info/top_level.txt
